{
  "cities": [
    {
      "cityName": "Lisbon",
      "country": "Portugal",
      "emoji": "pt",
      "date": "2027-10-31T15:59:59.138Z",
      "notes": "My favorite city so far!",
      "position": {
        "lat": 38.727881642324164,
        "lng": -9.140900099907554
      },
      "id": "73930385"
    },
    {
      "cityName": "Madrid",
      "country": "Spain",
      "emoji": "es",
      "date": "2027-07-15T08:22:53.976Z",
      "notes": "",
      "position": {
        "lat": 40.46635901755316,
        "lng": -3.7133789062500004
      },
      "id": "17806751"
    },
    {
      "cityName": "Berlin",
      "country": "Germany",
      "emoji": "de",
      "date": "2027-02-12T09:24:11.863Z",
      "notes": "Amazing 😃",
      "position": {
        "lat": 52.53586782505711,
        "lng": 13.376933665713324
      },
      "id": "98443197"
    },
    {
      "cityName": "Nijar",
      "country": "Spain",
      "emoji": "es",
      "date": "2023-04-03T07:47:59.202Z",
      "notes": "",
      "position": {
        "lat": "36.967508314568164",
        "lng": "-2.13128394200588"
      },
      "id": "98443198"
    },
    {
      "id": "7fa8",
      "cityName": "Ramecourt",
      "country": "France",
      "date": "2024-05-10T17:04:37.443Z",
      "notes": "23",
      "position": {
        "lat": "50.3454604086048",
        "lng": "2.3071289062500004"
      },
      "emoji": "FR"
    },
    {
      "id": "0888",
      "cityName": "Sabden",
      "country": "United Kingdom of Great Britain and Northern Ireland (the)",
      "date": "2024-05-10T17:17:48.075Z",
      "notes": "good",
      "position": {
        "lat": "53.839563678833606",
        "lng": "-2.3510742187500004"
      },
      "emoji": "GB"
    },
    {
      "id": "0fc1",
      "cityName": "Pontcarre",
      "country": "France",
      "date": "2024-05-10T17:19:48.202Z",
      "notes": "good",
      "position": {
        "lat": "48.79239019646409",
        "lng": "2.7246093750000004"
      },
      "emoji": "FR"
    },
    {
      "id": "f445",
      "cityName": "Coesfeld",
      "country": "Germany",
      "date": "2024-05-10T17:27:41.410Z",
      "notes": "",
      "position": {
        "lat": "51.89511914102238",
        "lng": "7.22243882812499"
      },
      "emoji": "DE"
    },
    {
      "id": "64cb",
      "cityName": "Vang",
      "country": "Norway",
      "date": "2024-05-10T17:27:52.427Z",
      "notes": "",
      "position": {
        "lat": "61.18562468142283",
        "lng": "8.789062500000002"
      },
      "emoji": "NO"
    },
    {
      "id": "201c",
      "cityName": "Sunndal",
      "country": "Norway",
      "date": "2024-05-10T17:29:09.158Z",
      "notes": "",
      "position": {
        "lat": "62.55285695857292",
        "lng": "9.096679687500002"
      },
      "emoji": "NO"
    }
  ]
}